pyDive/cloned_ndarray
pyDive/test
pyDive/arrays/local
pyDive/distribution
pyDive
pyDive/arrays
