Metadata-Version: 1.1
Name: pyDive
Version: 1.2.2
Summary: Distributed Interactive Visualization and Exploration of large datasets
Home-page: http://github.com/ComputationalRadiationPhysics/pyDive
Author: Heiko Burau
Author-email: h.burau@hzdr.de
License: GNU Affero General Public License v3
Platform: any
Classifier: Programming Language :: Python
Classifier: Development Status :: 4 - Beta
Classifier: Natural Language :: English
Classifier: Environment :: Console
Classifier: Environment :: Web Environment
Classifier: Intended Audience :: Science/Research
Classifier: License :: OSI Approved :: GNU Affero General Public License v3
Classifier: Operating System :: OS Independent
Classifier: Topic :: Scientific/Engineering :: Information Analysis
